Electronics lock/design.sv
// Code your design here
module electronics_lock(input clk,reset,b0,b1,output unlock);
  parameter S_RESET=0;
  parameter S_0=1;
  parameter S_01=2;
  parameter S_010=3;
  parameter S_0101=4;
  parameter S_01011=5;
  reg [2:0]state,next_state;
  always @(*)begin
    if(reset) next_state=S_RESET;
    else
      case(state)
      S_RESET:next_state=b0?S_0  :b1?S_RESET:state;
      S_0:    next_state=b0?S_0  :b1?S_01   :state;
      S_01:   next_state=b0?S_010:b1?S_RESET:state;
      S_010:  next_state=b0?S_0  :b1?S_0101 :state;
      S_0101: next_state=b0?S_010:b1?S_01011:state;
      S_01011:next_state=b0?S_0  :b1?S_RESET:state;
      default:next_state=S_RESET;
    endcase
  end
  always @(posedge clk)
    state<=next_state;
  
  assign unlock=state==S_01011?1:0;
endmodule

Electronics lock/testbench.sv
// Code your testbench here
// or browse Examples
module tb;
  reg clk,b0,b1,reset;
  wire unlock;
  integer i;
  reg [4:0] data;
  always #10 clk= ~clk;
  electronics_lock u0(clk,reset,b0,b1,unlock);
  initial begin
    $monitor("i=%0d,Time=%0d,reset=%b,b0=%b,b1=%b,unlock=%b",i,$time,reset,b0,b1,unlock);
    $dumpfile("tb.vcd");
    $dumpvars(1,tb);
    clk=0;
    reset=1;
    #50 reset=0;
    data=5'b01011;
    i=0;
    #130 $finish;
  end
  always @(posedge clk) begin
    b0=data[5-i]?0:1;
    b1=data[5-i]?1:0;
    i=i+1;
  end
endmodule

Electronics lock/tb.vcd
$date
    Jun  3, 2023  14:24:03
$end
$version
    TOOL:	xmsim	20.09-s003
$end
$timescale
    1 ns
$end

$scope module tb $end
$var reg       1 !    clk $end
$var reg       1 "    b0 $end
$var reg       1 #    b1 $end
$var reg       1 $    reset $end
$var wire      1 %    unlock  $end
$var integer  32 &    i $end
$var reg       5 '    data [4:0] $end
$upscope $end

$enddefinitions $end
$dumpvars
0!
x"
x#
1$
x%
bx &
bx '
$end
#10
1!
0%
#20
0!
#30
1!
#40
0!
#50
0$
b1011 '
b0 &
1!
b1 &
#60
0!
#70
1!
1"
0#
b10 &
#80
0!
#90
1!
0"
1#
b11 &
#100
0!
#110
1!
1"
0#
b100 &
#120
0!
#130
1!
0"
1#
b101 &
#140
0!
#150
1!
b110 &
1%
#160
0!
#170
1!
x"
x#
b111 &
x%
